ccl/__init__.py
ccl/finder.py
ccl/py.typed
clickloader-0.2.0.dist-info/LICENSE
clickloader-0.2.0.dist-info/METADATA
clickloader-0.2.0.dist-info/WHEEL
clickloader-0.2.0.dist-info/RECORD
