Metadata-Version: 2.1
Name: clickloader
Version: 0.2.0
Summary: Click Command Loader, permit to load Click command from a given folder.
Home-page: https://github.com/madebylydia/CCL
Author: Julien Mauroy
Author-email: pro.julien.mauroy@gmail.com
Requires-Python: >=3.7,<4.0
Classifier: Programming Language :: Python :: 3
Classifier: Programming Language :: Python :: 3.7
Classifier: Programming Language :: Python :: 3.8
Classifier: Programming Language :: Python :: 3.9
Classifier: Programming Language :: Python :: 3.10
Classifier: Programming Language :: Python :: 3.11
Requires-Dist: click (>=8.0)
Project-URL: Repository, https://github.com/madebylydia/CCL
